vidtoolz/__init__.py
vidtoolz/__main__.py
vidtoolz/cli.py
vidtoolz/hookspecs.py
vidtoolz/plugins.py
vidtoolz/utils.py
vidtoolz/default_plugins/__init__.py
vidtoolz/default_plugins/reverse.py
vidtoolz-0.1.4.dist-info/licenses/LICENSE
vidtoolz-0.1.4.dist-info/METADATA
vidtoolz-0.1.4.dist-info/WHEEL
vidtoolz-0.1.4.dist-info/entry_points.txt
vidtoolz-0.1.4.dist-info/top_level.txt
vidtoolz-0.1.4.dist-info/RECORD
