Metadata-Version: 2.4
Name: vidtoolz
Version: 0.1.4
Summary: CLI tools for editing videos in python. A plugin based approach.
Home-page: https://github.com/sukhbinder/vidtoolz
Author: Sukhbinder Singh
Project-URL: Documentation, https://sukhbinder.wordpress.com
Project-URL: Issues, https://github.com/sukhbinder/vidtoolz/issues
Project-URL: CI, https://github.com/sukhbinder/vidtoolz/actions
Project-URL: Changelog, https://github.com/sukhbinder/vidtoolz/releases
Classifier: Development Status :: 5 - Production/Stable
Classifier: Intended Audience :: Developers
Classifier: Intended Audience :: Science/Research
Classifier: Intended Audience :: End Users/Desktop
Classifier: Topic :: Database
Classifier: License :: OSI Approved :: Apache Software License
Classifier: Programming Language :: Python :: 3.8
Classifier: Programming Language :: Python :: 3.9
Classifier: Programming Language :: Python :: 3.10
Classifier: Programming Language :: Python :: 3.11
Classifier: Programming Language :: Python :: 3.12
Classifier: Programming Language :: Python :: 3.13
Requires-Python: >=3.9
License-File: LICENSE
Requires-Dist: pluggy
Requires-Dist: moviepy
Requires-Dist: imageio-ffmpeg
Requires-Dist: pip
Dynamic: author
Dynamic: classifier
Dynamic: description
Dynamic: description-content-type
Dynamic: home-page
Dynamic: license-file
Dynamic: project-url
Dynamic: requires-dist
Dynamic: requires-python
Dynamic: summary
